indented_logger/__init__.py
indented_logger/decorator.py
indented_logger/formatter.py
indented_logger/indent.py
indented_logger/log_indent_switcher.py
indented_logger/logging_config.py
indented_logger/old_structured_logging_setup.py
indented_logger/old_structured_processors.py
indented_logger/smart_logger.py
indented_logger/structured_logging_setup.py
indented_logger/structured_processors.py
indented_logger-0.3.5.dist-info/METADATA
indented_logger-0.3.5.dist-info/WHEEL
indented_logger-0.3.5.dist-info/top_level.txt
indented_logger-0.3.5.dist-info/RECORD
